hues/.hues.yml
hues/__init__.py
hues/colortable.py
hues/console.py
hues/dpda.py
hues/huestr.py
hues-0.2.2.dist-info/DESCRIPTION.rst
hues-0.2.2.dist-info/METADATA
hues-0.2.2.dist-info/RECORD
hues-0.2.2.dist-info/WHEEL
hues-0.2.2.dist-info/metadata.json
hues-0.2.2.dist-info/top_level.txt
