Metadata-Version: 1.1
Name: hues
Version: 0.2.2
Summary: Colored terminal text made easy for Python and happiness.
Home-page: https://github.com/prashnts/hues
Author: Prashant Sinha
Author-email: prashant@noop.pw
License: MIT
Download-URL: https://github.com/prashnts/hues/tarball/0.2.2
Keywords: color colour terminal text ansi hues unicorns console
Platform: UNKNOWN
Classifier: Development Status :: 3 - Alpha
Classifier: Intended Audience :: Developers
Classifier: License :: OSI Approved :: MIT License
Classifier: Programming Language :: Python
Classifier: Programming Language :: Python :: 2
Classifier: Programming Language :: Python :: 2.7
Classifier: Programming Language :: Python :: 3
Classifier: Programming Language :: Python :: 3.3
Classifier: Programming Language :: Python :: 3.4
Classifier: Topic :: Software Development :: Libraries :: Python Modules
